ttree/__init__.py
ttree/common.py
ttree/exceptions.py
ttree/node.py
ttree/tree.py
ttree/utils.py
ttree-1.0.3.dist-info/DESCRIPTION.rst
ttree-1.0.3.dist-info/METADATA
ttree-1.0.3.dist-info/RECORD
ttree-1.0.3.dist-info/WHEEL
ttree-1.0.3.dist-info/metadata.json
ttree-1.0.3.dist-info/top_level.txt
