Metadata-Version: 2.0
Name: ttree
Version: 1.0.3
Summary: Taxonomy tree data structure implementation.
Home-page: https://github.com/vovanbo/ttree
Author: Vladimir Bolshakov
Author-email: vovanbo@gmail.com
License: Apache License, Version 2.0
Keywords: data structure,tree,tools,taxonomy
Platform: UNKNOWN
Classifier: Development Status :: 4 - Beta
Classifier: Environment :: Console
Classifier: Intended Audience :: Developers
Classifier: License :: Freely Distributable
Classifier: Operating System :: OS Independent
Classifier: Programming Language :: Python
Classifier: Programming Language :: Python :: 3
Classifier: Programming Language :: Python :: 3.6
Classifier: Topic :: Software Development :: Libraries :: Python Modules
